pydevice42/__init__.py
pydevice42/__main__.py
pydevice42/basicrestclient.py
pydevice42/d42client.py
pydevice42/exceptions.py
pydevice42/logger.py
pydevice42/py.typed
pydevice42/types.py
pydevice42-0.4.1.dist-info/LICENSE
pydevice42-0.4.1.dist-info/WHEEL
pydevice42-0.4.1.dist-info/METADATA
pydevice42-0.4.1.dist-info/RECORD
