Metadata-Version: 2.1
Name: pydevice42
Version: 0.4.1
Summary: Python library to interact with Device42
Home-page: https://github.com/post-luxembourg/pydevice42
License: GPL-3.0-only
Author: Joaquim Esteves
Author-email: joaquimbve@hotmail.com
Requires-Python: >=3.8,<4.0
Classifier: License :: OSI Approved :: GNU General Public License v3 (GPLv3)
Classifier: Programming Language :: Python :: 3
Classifier: Programming Language :: Python :: 3.8
Classifier: Programming Language :: Python :: 3.9
Classifier: Typing :: Typed
Requires-Dist: requests (>=2.25.0,<3.0.0)
